django_orion_model/__init__.py
django_orion_model/admin.py
django_orion_model/apps.py
django_orion_model/extra.py
django_orion_model/tests.py
django_orion_model/urls.py
django_orion_model/views.py
django_orion_model/migrations/0001_initial.py
django_orion_model/migrations/0002_auto_20190829_1937.py
django_orion_model/migrations/__init__.py
django_orion_model/models/__init__.py
django_orion_model/models/connectors.py
django_orion_model/models/entities.py
django_orion_model/models/fields.py
django_orion_model/models/translation.py
django_orion_model-0.92.dist-info/LICENSE.txt
django_orion_model-0.92.dist-info/METADATA
django_orion_model-0.92.dist-info/WHEEL
django_orion_model-0.92.dist-info/top_level.txt
django_orion_model-0.92.dist-info/RECORD
