Metadata-Version: 2.1
Name: django-orion-model
Version: 0.92
Summary: A Django model to manage Fiware Orion Entities as local models 
Home-page: https://github.com/deusto-tech/django-orion-model/
Author: Josu Bermudez
Author-email: josu.bermudez@deusto.es
License: UNKNOWN
Project-URL: Bug Reports, https://github.com/deusto-tech/django-orion-model/issues
Project-URL: Source, https://github.com/deusto-tech/django-orion-model
Keywords: Fiware Orion development
Platform: UNKNOWN
Classifier: Development Status :: 4 - Beta
Classifier: Intended Audience :: Developers
Classifier: Topic :: Software Development :: Libraries
Classifier: Topic :: Software Development :: Libraries :: Python Modules
Classifier: License :: OSI Approved :: GNU General Public License v3 (GPLv3)
Classifier: Programming Language :: Python :: 3
Classifier: Programming Language :: Python :: 3.4
Classifier: Programming Language :: Python :: 3.5
Classifier: Programming Language :: Python :: 3.6
Classifier: Framework :: Django :: 2.0
Requires-Dist: django
Requires-Dist: pyfiware
